rbinstall/__init__.py
rbinstall/distro_info.py
rbinstall/errors.py
rbinstall/install_methods.py
rbinstall/install_steps.py
rbinstall/main.py
rbinstall/process.py
rbinstall/pypi.py
rbinstall/state.py
rbinstall/ui.py
rbinstall/versioning.py
rbinstall/wizard.py
rbinstall-1.2.1.dist-info/AUTHORS
rbinstall-1.2.1.dist-info/COPYING
rbinstall-1.2.1.dist-info/METADATA
rbinstall-1.2.1.dist-info/WHEEL
rbinstall-1.2.1.dist-info/entry_points.txt
rbinstall-1.2.1.dist-info/top_level.txt
rbinstall-1.2.1.dist-info/RECORD
