Metadata-Version: 2.1
Name: rbinstall
Version: 1.2.1
Summary: Official installer for Review Board code/document review.
Author-email: "Beanbag, Inc." <questions@beanbaginc.com>
License: Copyright (c) 2023  Beanbag, Inc.
Project-URL: homepage, https://github.com/reviewboard/rbinstall
Project-URL: documentation, https://github.com/reviewboard/rbinstall
Project-URL: repository, https://github.com/reviewboard/rbinstall
Classifier: Development Status :: 5 - Production/Stable
Classifier: Environment :: Console
Classifier: Intended Audience :: Developers
Classifier: Intended Audience :: System Administrators
Classifier: License :: OSI Approved :: MIT License
Classifier: Operating System :: MacOS
Classifier: Operating System :: MacOS :: MacOS X
Classifier: Operating System :: POSIX :: Linux
Classifier: Programming Language :: Python
Classifier: Programming Language :: Python :: 3
Classifier: Programming Language :: Python :: 3.7
Classifier: Programming Language :: Python :: 3.8
Classifier: Programming Language :: Python :: 3.9
Classifier: Programming Language :: Python :: 3.10
Classifier: Programming Language :: Python :: 3.11
Classifier: Programming Language :: Python :: 3.12
Classifier: Topic :: System
Classifier: Topic :: System :: Installation/Setup
Classifier: Topic :: System :: Software Distribution
Classifier: Topic :: System :: Systems Administration
Requires-Python: >=3.7
License-File: COPYING
License-File: AUTHORS
Requires-Dist: packaging~=23.2
Requires-Dist: rich~=13.7.0
Requires-Dist: typing-extensions>=4.3.0
Requires-Dist: virtualenv
